{
 "banana": 33.0,
 "barrel": 13.0,
 "bnc": 35.6,
 "db25_f": 53.1,
 "db25_m": 53.1,
 "db37_f": 69.4,
 "db37_m": 69.4,
 "db9_f": 30.8,
 "db9_m": 30.8,
 "din41612_f": 94.9,
 "din41612_m": 94.0,
 "dvi": 36.8,
 "fmc": 56.7,
 "hd15_f": 30.8,
 "hd15_m": 30.8,
 "hdmi_a": 16.2,
 "hdmi_micro": 7.5,
 "idc": 33.1,
 "ide40": 58.5,
 "iec_c14": 65.0,
 "jack35": 14.3,
 "lemo": 17.5,
 "lemo_elbow": 17.5,
 "mmcx": 7.4,
 "molex_kk": 15.3,
 "p_amc_edge": 74.0,
 "p_atca_zone2": 46.0,
 "p_bnc_plug": 41.3,
 "p_button": 19.6,
 "p_dac": 95.3,
 "p_df57": 14.2,
 "p_din716": 56.5,
 "p_dip": 20.0,
 "p_displayport": 37.3,
 "p_e2000": 38.6,
 "p_f_type": 31.5,
 "p_fc": 35.0,
 "p_firefly": 40.6,
 "p_firewire6": 33.2,
 "p_firewire9": 30.7,
 "p_gpib": 59.8,
 "p_hdmi_mini": 26.7,
 "p_lc": 28.8,
 "p_lc_duplex": 28.8,
 "p_m2": 62.0,
 "p_matenlok": 24.8,
 "p_mhv": 27.8,
 "p_microfit": 10.7,
 "p_minifit": 13.9,
 "p_minisas_hd": 57.1,
 "p_mt_ferrule": 23.0,
 "p_mtp": 39.5,
 "p_mtp_apc": 39.7,
 "p_mtp_f": 39.2,
 "p_mu": 28.0,
 "p_nim_conn": 74.0,
 "p_powerpole": 25.0,
 "p_qsfp": 92.0,
 "p_radiall_hv": 56.3,
 "p_rca": 38.2,
 "p_redel": 47.1,
 "p_rj11": 29.5,
 "p_rj45_plug": 36.7,
 "p_sas": 44.0,
 "p_sc": 44.0,
 "p_sfp": 66.6,
 "p_shv": 34.8,
 "p_shv_plug": 45.4,
 "p_smp": 12.2,
 "p_splice": 46.0,
 "p_st": 36.5,
 "p_toslink": 37.7,
 "p_triax": 30.2,
 "p_twinbnc": 40.8,
 "p_uhf": 41.0,
 "p_usb3_b": 34.9,
 "p_usb3_micro": 24.1,
 "p_vtrx": 48.0,
 "p_xlr_f": 41.5,
 "p_xlr_m": 45.2,
 "rj45": 18.7,
 "rj45_h": 25.4,
 "sata": 42.4,
 "sma": 8.8,
 "sma_edge": 19.5,
 "ufl": 3.1,
 "usb_a": 15.4,
 "usb_a_h": 16.1,
 "usb_c": 10.5,
 "usb_c_h": 8.9,
 "usb_micro": 8.0,
 "usb_mini": 9.9,
 "v_accuglass_110177_mhv": 54.9,
 "v_accuglass_112441_shv5": 74.9,
 "v_adamtech_dpc-f-s-ra-smt-bl": 21.3,
 "v_adamtech_mchdmi-s-ra-1-smt": 8.9,
 "v_adamtech_qsfp1-dd-emi-hsk-lp-s3": 71.7,
 "v_adamtech_rj11_plug": 14.4,
 "v_adamtech_rj45_plug": 22.4,
 "v_adamtech_sfc-1-emi": 48.8,
 "v_anderson_pp15-45": 24.7,
 "v_bkl_f_plug": 20.1,
 "v_cliff_fc": 31.0,
 "v_cliff_fcr684205r": 23.1,
 "v_neutrik_lc_duplex": 34.3,
 "v_neutrik_nc3mxx": 69.6,
 "v_neutrik_no2-4fdw-a": 34.3,
 "v_norcomp_111-024-113L001": 54.7,
 "v_qualtek_744w-00-01": 53.0,
 "v_radiall_716_plug": 48.6,
 "v_radiall_bnc_plug": 28.0,
 "v_radiall_mhv_plug": 37.5,
 "v_radiall_n_plug": 38.5,
 "v_radiall_shv_jack": 46.2,
 "v_radiall_shv_plug": 53.2,
 "v_radiall_smp": 8.5,
 "v_radiall_tnc_plug": 26.2,
 "v_samesky_rcj-041": 19.5,
 "v_wurth_60412042241503": 30.0,
 "v_wurth_61400416121": 16.5,
 "v_wurth_615004138421": 17.8,
 "v_wurth_61611002121501": 14.1,
 "v_wurth_643150100604": 24.5,
 "v_wurth_643160100604": 24.2,
 "v_wurth_649004113322": 19.6,
 "v_wurth_67012002221502": 17.2
}